odoo/addons/geoengine_partner/README.rst
odoo/addons/geoengine_partner/__init__.py
odoo/addons/geoengine_partner/__manifest__.py
odoo/addons/geoengine_partner/i18n/geoengine_partner.pot
odoo/addons/geoengine_partner/i18n/it.po
odoo/addons/geoengine_partner/i18n/zh_CN.po
odoo/addons/geoengine_partner/models/__init__.py
odoo/addons/geoengine_partner/models/partner.py
odoo/addons/geoengine_partner/readme/CONTRIBUTORS.md
odoo/addons/geoengine_partner/readme/DESCRIPTION.md
odoo/addons/geoengine_partner/readme/INSTALL.md
odoo/addons/geoengine_partner/readme/USAGE.md
odoo/addons/geoengine_partner/static/description/icon.png
odoo/addons/geoengine_partner/static/description/index.html
odoo/addons/geoengine_partner/views/partner.xml
odoo_addon_geoengine_partner-17.0.1.0.0.4.dist-info/METADATA
odoo_addon_geoengine_partner-17.0.1.0.0.4.dist-info/WHEEL
odoo_addon_geoengine_partner-17.0.1.0.0.4.dist-info/top_level.txt
odoo_addon_geoengine_partner-17.0.1.0.0.4.dist-info/RECORD
